rehline/__init__.py
rehline/_base.py
rehline/_class.py
rehline/_data.py
rehline/_internal.cp313-win32.pyd
rehline/_loss.py
rehline/_path_sol.py
rehline/_sklearn_mixin.py
rehline-0.1.1.dist-info/licenses/LICENSE
rehline-0.1.1.dist-info/METADATA
rehline-0.1.1.dist-info/WHEEL
rehline-0.1.1.dist-info/top_level.txt
rehline-0.1.1.dist-info/RECORD
