Metadata-Version: 2.4
Name: rehline
Version: 0.1.1
Summary: Regularized Composite ReLU-ReHU Loss Minimization with Linear Computation and Linear Convergence
Home-page: https://rehline-python.readthedocs.io/en/latest/
Author: ['Ben Dai', 'Yixuan Qiu']
Author-email: Ben Dai <bendai@cuhk.edu.hk>, Yixuan Qiu <yixuanq@gmail.com>
Maintainer-email: Ben Dai <bendai@cuhk.edu.hk>
License: MIT License
Requires-Python: >= 3.10
License-File: LICENSE
Requires-Dist: numpy>=1.23.5
Requires-Dist: scipy>=1.11.4
Requires-Dist: scikit-learn>=1.2.2
Dynamic: author
Dynamic: home-page
Dynamic: license-file
Dynamic: requires-python
